easyparse/__init__.py
easyparse/easyparse.py
easyparse/terminal_colors.py
easyparse-1.0.6.dist-info/LICENSE
easyparse-1.0.6.dist-info/WHEEL
easyparse-1.0.6.dist-info/METADATA
easyparse-1.0.6.dist-info/RECORD
