Metadata-Version: 2.1
Name: easyparse
Version: 1.0.6
Summary: A user-friendly, lightweight command-line argument parser.
Home-page: https://github.com/Sh3llcod3/Easyparse
License: MIT
Author: Yudhajit N
Author-email: 28938427+Sh3llcod3@users.noreply.github.com
Requires-Python: >=3.6,<4.0
Classifier: Environment :: Console
Classifier: License :: OSI Approved :: MIT License
Classifier: Operating System :: POSIX :: Linux
Classifier: Programming Language :: Python :: 3
Classifier: Programming Language :: Python :: 3.6
Classifier: Programming Language :: Python :: 3.7
Classifier: Programming Language :: Python :: 3.8
Project-URL: Repository, https://github.com/Sh3llcod3/Easyparse
